ai_bot_agent/__init__.py
ai_bot_agent/main.py
ai_bot_agent-1.6.0.dist-info/licenses/LICENSE
ai_bot_agent-1.6.0.dist-info/METADATA
ai_bot_agent-1.6.0.dist-info/WHEEL
ai_bot_agent-1.6.0.dist-info/entry_points.txt
ai_bot_agent-1.6.0.dist-info/top_level.txt
ai_bot_agent-1.6.0.dist-info/RECORD
