Metadata-Version: 2.4
Name: ai-bot-agent
Version: 1.6.0
Summary: 🤖 AI Bot Agent - Intelligent command line assistant with chat, code generation, file analysis, and web search capabilities
Author-email: Thien Nguyen <thien.nguyen@check24.de>
Maintainer-email: Thien Nguyen <thien.nguyen@check24.de>
License: MIT
Project-URL: Homepage, https://github.com/thiennp/cli-smart
Project-URL: Documentation, https://github.com/thiennp/cli-smart#readme
Project-URL: Repository, https://github.com/thiennp/cli-smart
Project-URL: Bug Tracker, https://github.com/thiennp/cli-smart/issues
Project-URL: Changelog, https://github.com/thiennp/cli-smart/blob/main/README.md#version-history
Keywords: ai,cli,openai,chatbot,assistant,code-generation
Classifier: Development Status :: 4 - Beta
Classifier: Intended Audience :: Developers
Classifier: Operating System :: OS Independent
Classifier: Programming Language :: Python :: 3
Classifier: Programming Language :: Python :: 3.8
Classifier: Programming Language :: Python :: 3.9
Classifier: Programming Language :: Python :: 3.10
Classifier: Programming Language :: Python :: 3.11
Classifier: Programming Language :: Python :: 3.12
Classifier: Topic :: Software Development :: Libraries :: Python Modules
Classifier: Topic :: Scientific/Engineering :: Artificial Intelligence
Classifier: Topic :: System :: Shells
Classifier: Topic :: Utilities
Requires-Python: >=3.8
License-File: LICENSE
Requires-Dist: openai>=1.0.0
Requires-Dist: click>=8.0.0
Requires-Dist: rich>=13.0.0
Requires-Dist: python-dotenv>=1.0.0
Requires-Dist: requests>=2.31.0
Requires-Dist: typer>=0.9.0
Requires-Dist: colorama>=0.4.6
Provides-Extra: dev
Requires-Dist: pytest>=7.0.0; extra == "dev"
Requires-Dist: black>=22.0.0; extra == "dev"
Requires-Dist: flake8>=5.0.0; extra == "dev"
Requires-Dist: mypy>=1.0.0; extra == "dev"
Dynamic: license-file
